setup.py
pylods_json.egg-info/PKG-INFO
pylods_json.egg-info/SOURCES.txt
pylods_json.egg-info/dependency_links.txt
pylods_json.egg-info/requires.txt
pylods_json.egg-info/top_level.txt
pylodsjson/__init__.py
pylodsjson/pylodsjson.py