Metadata-Version: 1.1
Name: pylods-json
Version: 0.3.6
Summary: json extension for pylods msgpack
Home-page: https://github.com/salimm/pylods-ijson
Author: Salim Malakouti
Author-email: salim.malakouti@gmail.com
License: MIT
Download-URL: http://github.com/salimm/pylods-json/archive/0.3.6.tar.gz
Keywords: python,serialization,deserialization,paser,json,object oriented,fast,extendable,type based,jackson json,ijson
Platform: UNKNOWN
Classifier: Programming Language :: Python
